wheelbarrow/__init__.py
wheelbarrow/py.typed
wheelbarrow/albert/__init__.py
wheelbarrow/albert/errorprop.py
wheelbarrow/david/__init__.py
wheelbarrow/huxley/__init__.py
wheelbarrow/jack/__init__.py
wheelbarrow/zach/__init__.py
andco_wheelbarrow-0.2.2.dist-info/METADATA
andco_wheelbarrow-0.2.2.dist-info/WHEEL
andco_wheelbarrow-0.2.2.dist-info/RECORD
